MANIFEST.in
README.rst
setup.py
ripozo_cassandra/__init__.py
ripozo_cassandra/cqlmanager.py
ripozo_cassandra.egg-info/PKG-INFO
ripozo_cassandra.egg-info/SOURCES.txt
ripozo_cassandra.egg-info/dependency_links.txt
ripozo_cassandra.egg-info/requires.txt
ripozo_cassandra.egg-info/top_level.txt