Metadata-Version: 1.1
Name: ripozo-cassandra
Version: 0.2.1
Summary: Integrates cassandra/cqlengine with ripozo to easily create cassandra backed Hypermedia/HATEOAS/REST apis
Home-page: UNKNOWN
Author: Tim Martin
Author-email: tim.martin@vertical-knowledge.com
License: UNKNOWN
Platform: UNKNOWN
Classifier: Development Status :: 3 - Alpha
Classifier: License :: Other/Proprietary License
Classifier: Operating System :: OS Independent
Classifier: Programming Language :: Python
Classifier: Programming Language :: Python :: 2
Classifier: Programming Language :: Python :: 2.6
Classifier: Programming Language :: Python :: 2.7
Classifier: Programming Language :: Python :: 3
Classifier: Programming Language :: Python :: 3.3
Classifier: Programming Language :: Python :: 3.4
Classifier: Programming Language :: Python :: Implementation :: PyPy
Classifier: Topic :: Software Development :: Libraries :: Python Modules
